tailchaser/__init__.py
tailchaser/__main__.py
tailchaser/cli.py
tailchaser/pipes.py
tailchaser/tailer.py
tailchaser-0.2.6.dist-info/DESCRIPTION.rst
tailchaser-0.2.6.dist-info/METADATA
tailchaser-0.2.6.dist-info/RECORD
tailchaser-0.2.6.dist-info/WHEEL
tailchaser-0.2.6.dist-info/entry_points.txt
tailchaser-0.2.6.dist-info/metadata.json
tailchaser-0.2.6.dist-info/top_level.txt
