Metadata-Version: 2.0
Name: tailchaser
Version: 0.2.6
Summary: the ultimate tailer
Home-page: https://github.com/thanos/tailchaser
Author: thanos vassilakis
Author-email: thanosv@gmail.com
License: BSD
Keywords: tail,watch,logs
Platform: UNKNOWN
Classifier: Development Status :: 5 - Production/Stable
Classifier: Intended Audience :: Developers
Classifier: License :: OSI Approved :: BSD License
Classifier: Operating System :: Unix
Classifier: Operating System :: POSIX
Classifier: Operating System :: Microsoft :: Windows
Classifier: Programming Language :: Python
Classifier: Programming Language :: Python :: 2.7
Classifier: Programming Language :: Python :: Implementation :: CPython
Classifier: Programming Language :: Python :: Implementation :: PyPy
Classifier: Topic :: Utilities
Requires-Dist: regex (==2016.04.25)
Requires-Dist: six (==1.10.0)
Provides-Extra: rst
Requires-Dist: docutils (>=0.11); extra == 'rst'
